maggy/__init__.py
maggy/callbacks.py
maggy/constants.py
maggy/experiment.py
maggy/searchspace.py
maggy/tensorboard.py
maggy/trial.py
maggy/util.py
maggy/version.py
maggy/ablation/__init__.py
maggy/ablation/ablationstudy.py
maggy/ablation/ablator/__init__.py
maggy/ablation/ablator/abstractablator.py
maggy/ablation/ablator/loco.py
maggy/core/__init__.py
maggy/core/config.py
maggy/core/exceptions.py
maggy/core/experimentdriver.py
maggy/core/reporter.py
maggy/core/rpc.py
maggy/core/trialexecutor.py
maggy/earlystop/__init__.py
maggy/earlystop/abstractearlystop.py
maggy/earlystop/medianrule.py
maggy/earlystop/nostop.py
maggy/optimizer/__init__.py
maggy/optimizer/abstractoptimizer.py
maggy/optimizer/asha.py
maggy/optimizer/randomsearch.py
maggy/optimizer/singlerun.py
maggy/tests/__init__.py
maggy/tests/conftest.py
maggy/tests/test_maggy.py
maggy/tests/test_randomsearch.py
maggy/tests/test_searchspace.py
maggy/tests/test_trial.py
maggy/tests/test_wordcount.py
maggy-0.5.3.dist-info/LICENSE
maggy-0.5.3.dist-info/METADATA
maggy-0.5.3.dist-info/WHEEL
maggy-0.5.3.dist-info/top_level.txt
maggy-0.5.3.dist-info/RECORD
