Metadata-Version: 2.1
Name: maggy
Version: 0.5.3
Summary: Efficient asynchronous optimization of expensive black-box functions on top of Apache Spark
Home-page: https://github.com/logicalclocks/maggy
Author: Moritz Meister
Author-email: meister.mo@gmail.com
License: GNU Affero General Public License v3
Download-URL: http://snurran.sics.se/hops/maggy/maggy-0.5.3.tar.gz
Keywords: Hyperparameter,Optimization,Auto-ML,Hops,Hadoop,TensorFlow,Spark
Platform: UNKNOWN
Classifier: Development Status :: 2 - Pre-Alpha
Classifier: Topic :: Utilities
Classifier: License :: OSI Approved :: Apache Software License
Classifier: Programming Language :: Python :: 3
Requires-Dist: numpy
Provides-Extra: dev
Requires-Dist: black ; extra == 'dev'
Requires-Dist: flake8 ; extra == 'dev'
Provides-Extra: docs
Requires-Dist: sphinx (==1.8.5) ; extra == 'docs'
Requires-Dist: sphinx-autobuild ; extra == 'docs'
Requires-Dist: recommonmark ; extra == 'docs'
Requires-Dist: sphinx-rtd-theme ; extra == 'docs'
Requires-Dist: jupyter-sphinx-theme ; extra == 'docs'
Provides-Extra: pydoop
Requires-Dist: pydoop ; extra == 'pydoop'
Provides-Extra: spark
Requires-Dist: pyspark (==2.4.3) ; extra == 'spark'
Provides-Extra: test
Requires-Dist: pylint ; extra == 'test'
Requires-Dist: pytest ; extra == 'test'
Provides-Extra: tf
Requires-Dist: tensorflow (==1.14.0) ; extra == 'tf'
